{
    "modelName": "50 x 10m area",
    "record": "true",
    "dataModel": [
        {
            "dataType": "number",
            "name": "nonNativePlantCover"
        },
        {
            "columns": [{
                "dataType": "species",
                "dwcAttribute": "scientificName",
                "name": "shrubSpeciesName"
            }],
            "dataType": "list",
            "name": "shrubSpeciesRichness",
            "defaultRows": []
        },
        {
            "dataType": "number",
            "name": "numUnknownShrubSpecies"
        },
        {
            "columns": [{
                "dataType": "species",
                "dwcAttribute": "scientificName",
                "name": "grassSpeciesName"
            }],
            "dataType": "list",
            "name": "grassSpeciesRichness",
            "defaultRows": []
        },
        {
            "dataType": "number",
            "name": "numUnknownGrassSpecies"
        },
        {
            "columns": [{
                "dataType": "species",
                "dwcAttribute": "scientificName",
                "name": "forbSpeciesName"
            }],
            "dataType": "list",
            "name": "forbsAndOthersNonGrassGroundSpeciesRichness",
            "defaultRows": []
        },
        {
            "dataType": "number",
            "name": "numUnknownForbSpecies"
        }
    ],
    "viewModel": [
        {
            "type": "row",
            "items": [{
                "source": "<h3>50 x 10m area<\/h3>",
                "type": "literal"
            }]
        },
        {
            "type": "row",
            "items": [{
                "preLabel": "Non-native plant cover (%):",
                "source": "nonNativePlantCover",
                "type": "number",
                "validate": "required,min[0],max[100]"
            }]
        },
        {
            "type": "row",
            "items": [{
                "type": "col",
                "items": [
                    {
                        "source": "<h4>Shrub (defined as sungle stemmed below 2m or multi-stemmed from base or below 20cm) species richness:<\/h4>",
                        "type": "literal"
                    },
                    {
                        "columns": [{
                            "source": "shrubSpeciesName",
                            "title": "Species name",
                            "type": "text"
                        }],
                        "userAddedRows": "true",
                        "source": "shrubSpeciesRichness",
                        "type": "table"
                    },
                    {
                        "preLabel": "Number of unknown shrub species",
                        "source": "numUnknownShrubSpecies",
                        "type": "number",
                        "validate": "min[0]"
                    }
                ]
            }]
        },
        {
            "type": "row",
            "items": [{
                "type": "col",
                "items": [
                    {
                        "source": "<h4>Grass species richness<\/h4>",
                        "type": "literal"
                    },
                    {
                        "columns": [{
                            "source": "grassSpeciesName",
                            "title": "Species name",
                            "type": "text"
                        }],
                        "userAddedRows": "true",
                        "source": "grassSpeciesRichness",
                        "type": "table"
                    },
                    {
                        "preLabel": "Number of unknown grass species",
                        "source": "numUnknownGrassSpecies",
                        "type": "number",
                        "validate": "min[0]"
                    }
                ]
            }]
        },
        {
            "type": "row",
            "items": [{
                "type": "col",
                "items": [
                    {
                        "source": "<h4>Forbs and others (non grass ground) species richness:<\/h4>",
                        "type": "literal"
                    },
                    {
                        "columns": [{
                            "source": "forbSpeciesName",
                            "title": "Species name",
                            "type": "text"
                        }],
                        "userAddedRows": "true",
                        "source": "forbsAndOthersNonGrassGroundSpeciesRichness",
                        "type": "table"
                    },
                    {
                        "preLabel": "Number of unknown forb species",
                        "source": "numUnknownForbSpecies",
                        "type": "number",
                        "validate": "min[0]"
                    }
                ]
            }]
        }
    ]
}